README.md
setup.py
rebade/BackupEngine.py
rebade/CmdlineEscape.py
rebade/Configuration.py
rebade/Exceptions.py
rebade/FriendlyArgumentParser.py
rebade/MultiCommand.py
rebade/PrefixMatcher.py
rebade/StateFile.py
rebade/Tools.py
rebade/__init__.py
rebade/__main__.py
rebade.egg-info/PKG-INFO
rebade.egg-info/SOURCES.txt
rebade.egg-info/dependency_links.txt
rebade.egg-info/entry_points.txt
rebade.egg-info/requires.txt
rebade.egg-info/top_level.txt
rebade/actions/ActionBackup.py
rebade/actions/ActionDaemon.py
rebade/actions/ActionForget.py
rebade/actions/ActionGeneric.py
rebade/actions/ActionMount.py
rebade/actions/__init__.py