Metadata-Version: 2.1
Name: rebade
Version: 0.0.3
Summary: Restic backup daemon: a friendly frontend for restic
Home-page: https://github.com/johndoe31415/rebade
Download-URL: https://github.com/johndoe31415/rebade/archive/v0.0.3.tar.gz
Author: Johannes Bauer
Author-email: joe@johannes-bauer.com
License: gpl-3.0
Keywords: restic,backup,daemon
Classifier: Development Status :: 5 - Production/Stable
Classifier: Intended Audience :: Developers
Classifier: License :: OSI Approved :: GNU General Public License v3 (GPLv3)
Classifier: Programming Language :: Python :: 3
Classifier: Programming Language :: Python :: 3 :: Only
Classifier: Programming Language :: Python :: 3.10
Requires-Dist: requests
